jcmoptimizer/__init__.py
jcmoptimizer/benchmark.py
jcmoptimizer/client.py
jcmoptimizer/objects.py
jcmoptimizer/requestor.py
jcmoptimizer/server.py
jcmoptimizer/study.py
jcmoptimizer/version.py
jcmoptimizer/drivers/__init__.py
jcmoptimizer/drivers/active_learning_drivers.py
jcmoptimizer/drivers/driver.py
jcmoptimizer/drivers/third_party_drivers.py
jcmoptimizer-3.0.1.dist-info/licenses/LICENSE
jcmoptimizer-3.0.1.dist-info/METADATA
jcmoptimizer-3.0.1.dist-info/WHEEL
jcmoptimizer-3.0.1.dist-info/top_level.txt
jcmoptimizer-3.0.1.dist-info/RECORD
