Metadata-Version: 2.4
Name: jcmoptimizer
Version: 3.0.1
Summary: The JCMoptimizer interface for Python
Author-email: Philipp Schneider <philipp.schneider@jcmwave.com>
License-Expression: MIT
Project-URL: homepage, https://optimizer.jcmwave.com
Project-URL: documentation, https://optimizer.jcmwave.com/documentation/python/latest/interface/index.html
Project-URL: releasenotes, https://optimizer.jcmwave.com/release-notes
Classifier: Programming Language :: Python :: 3
Classifier: Operating System :: OS Independent
Requires-Python: >=3.9
License-File: LICENSE
Requires-Dist: requests
Requires-Dist: colorama
Dynamic: license-file
